copyright_stats_extractor/__init__.py
copyright_stats_extractor/main.py
copyright_stats_extractor/prompts.py
copyright_stats_extractor-2025.12.22110614.dist-info/METADATA
copyright_stats_extractor-2025.12.22110614.dist-info/WHEEL
copyright_stats_extractor-2025.12.22110614.dist-info/top_level.txt
copyright_stats_extractor-2025.12.22110614.dist-info/RECORD
