Metadata-Version: 2.4
Name: copyright-stats-extractor
Version: 2025.12.22110614
Summary: copyright-stats-extractor parses headlines/articles on digital copyright enforcement to auto‑extract stats like takedown counts, year, and parties.
Author-email: copyright-stats-extractor <hi@eugene.plus>
License: MIT
Project-URL: Homepage, https://github.com/chigwell/copyright-stats-extractor
Requires-Python: >=3.9
Requires-Dist: langchain-llm7>=0.0.0
Requires-Dist: llmatch-messages>=0.0.0
Requires-Dist: langchain-core>=0.3.0
